htexpr/__init__.py
htexpr/exceptions.py
htexpr/htexpr.py
htexpr/mappings.py
htexpr-0.1.2.dist-info/LICENSE
htexpr-0.1.2.dist-info/METADATA
htexpr-0.1.2.dist-info/WHEEL
htexpr-0.1.2.dist-info/top_level.txt
htexpr-0.1.2.dist-info/zip-safe
htexpr-0.1.2.dist-info/RECORD
