Metadata-Version: 2.1
Name: htexpr
Version: 0.1.2
Summary: htexpr compiles an html string into a Python expression
Home-page: https://github.com/jkseppan/htexpr
Author: Jouni K. Seppänen
Author-email: jks@iki.fi
License: MIT license
Classifier: Development Status :: 3 - Alpha
Classifier: Intended Audience :: Developers
Classifier: License :: OSI Approved :: MIT License
Classifier: Environment :: Web Environment
Classifier: Programming Language :: Python :: 3.8
Classifier: Programming Language :: Python :: 3.9
Classifier: Programming Language :: Python :: 3.10
Classifier: Programming Language :: Python :: 3.11
Classifier: Programming Language :: Python :: Implementation :: CPython
Classifier: Topic :: Software Development :: Code Generators
Classifier: Topic :: Text Processing :: Markup :: HTML
Classifier: Framework :: Dash
Requires-Python: >=3.8
License-File: LICENSE
Requires-Dist: parsimonious (<0.11,>=0.9.0)
Requires-Dist: toolz (<0.13,>=0.9)
Provides-Extra: dev
Requires-Dist: pytest (<7.3,>=6.0) ; extra == 'dev'
Requires-Dist: coverage (>=6.1.2) ; extra == 'dev'
Requires-Dist: pytest-sugar (~=0.9.3) ; extra == 'dev'
Requires-Dist: dash[testing] (<2.8,>=2.0.0) ; extra == 'dev'
Requires-Dist: dash-bootstrap-components (<2.0,>=1.0.0) ; extra == 'dev'
Requires-Dist: requests (<2.29,>=2.23) ; extra == 'dev'
Provides-Extra: examples
Requires-Dist: dash (<2.8,>=2.0.0) ; extra == 'examples'
Requires-Dist: dash-bootstrap-components (<2.0,>=1.0.0) ; extra == 'examples'
